plonestatic.euphorie-1.0.1-py3.13-nspkg.pth
plonestatic/euphorie/__init__.py
plonestatic/euphorie/configure.zcml
plonestatic/euphorie/resources/assets/css/style.css
plonestatic/euphorie/resources/assets/default/style/flags/flag_ad.svg
plonestatic/euphorie/resources/assets/default/style/flags/flag_al.svg
plonestatic/euphorie/resources/assets/default/style/flags/flag_am.svg
plonestatic/euphorie/resources/assets/default/style/flags/flag_ba.svg
plonestatic/euphorie/resources/assets/default/style/flags/flag_basque.svg
plonestatic/euphorie/resources/assets/default/style/flags/flag_catalonia.svg
plonestatic/euphorie/resources/assets/default/style/flags/flag_ch.svg
plonestatic/euphorie/resources/assets/default/style/flags/flag_cy.svg
plonestatic/euphorie/resources/assets/default/style/flags/flag_dk.svg
plonestatic/euphorie/resources/assets/default/style/flags/flag_es.svg
plonestatic/euphorie/resources/assets/default/style/flags/flag_eu.svg
plonestatic/euphorie/resources/assets/default/style/flags/flag_fi.svg
plonestatic/euphorie/resources/assets/default/style/flags/flag_gb.svg
plonestatic/euphorie/resources/assets/default/style/flags/flag_gr.svg
plonestatic/euphorie/resources/assets/default/style/flags/flag_hr.svg
plonestatic/euphorie/resources/assets/default/style/flags/flag_il.svg
plonestatic/euphorie/resources/assets/default/style/flags/flag_is.svg
plonestatic/euphorie/resources/assets/default/style/flags/flag_li.svg
plonestatic/euphorie/resources/assets/default/style/flags/flag_me.svg
plonestatic/euphorie/resources/assets/default/style/flags/flag_mk.svg
plonestatic/euphorie/resources/assets/default/style/flags/flag_mt.svg
plonestatic/euphorie/resources/assets/default/style/flags/flag_no.svg
plonestatic/euphorie/resources/assets/default/style/flags/flag_pt.svg
plonestatic/euphorie/resources/assets/default/style/flags/flag_rs.svg
plonestatic/euphorie/resources/assets/default/style/flags/flag_se.svg
plonestatic/euphorie/resources/assets/default/style/flags/flag_si.svg
plonestatic_euphorie-1.0.1.dist-info/METADATA
plonestatic_euphorie-1.0.1.dist-info/WHEEL
plonestatic_euphorie-1.0.1.dist-info/entry_points.txt
plonestatic_euphorie-1.0.1.dist-info/namespace_packages.txt
plonestatic_euphorie-1.0.1.dist-info/top_level.txt
plonestatic_euphorie-1.0.1.dist-info/RECORD
