Metadata-Version: 2.4
Name: plonestatic.euphorie
Version: 1.0.1
Summary: Euphorie Risk Assessment tool static resources
Home-page: https://github.com/euphorie/plonestatic.euphorie
Author: Syslab.com
Author-email: info@syslab.com
License: GPL
Project-URL: Homepage, https://github.com/euphorie
Project-URL: Source, https://github.com/euphorie/plonestatic.euphorie
Project-URL: Issues, https://github.com/euphorie/plonestatic.euphorie/issues
Keywords: euphorie OiRA Interactive Risk Assessment static resources
Classifier: Development Status :: 5 - Production/Stable
Classifier: Environment :: Web Environment
Classifier: Framework :: Plone
Classifier: Framework :: Plone :: 6.0
Classifier: License :: OSI Approved :: GNU General Public License (GPL)
Classifier: Programming Language :: Python :: 3
Classifier: Programming Language :: Python :: 3.9
Classifier: Programming Language :: Python :: 3.10
Classifier: Programming Language :: Python :: 3.11
Classifier: Programming Language :: Python :: 3.12
Classifier: Programming Language :: Python :: 3.13
Classifier: Topic :: Internet :: WWW/HTTP
Classifier: Topic :: Software Development :: Libraries :: Python Modules
Requires-Python: >= 3.9
Requires-Dist: Plone>=6.0
Requires-Dist: plone.patternslib
Provides-Extra: tests
Requires-Dist: plone.app.testing; extra == "tests"
Dynamic: author
Dynamic: author-email
Dynamic: classifier
Dynamic: description
Dynamic: description-content-type
Dynamic: home-page
Dynamic: keywords
Dynamic: license
Dynamic: project-url
Dynamic: provides-extra
Dynamic: requires-dist
Dynamic: requires-python
Dynamic: summary
